[
  {
    "id": 1,
    "name": "위코드런스 아로마틱 핸드 워시",
    "price": "47000.00",
    "description": "고유 코딩 실력이 함유되어 손을 씻을 때마다 200ok가 절로 나오는 핸드 워시",
    "sizeId": 4,
    "subCategoryId": 5,
    "size": "500ml",
    "subCategoryName": "핸드",
    "mainCategoryId": 3,
    "mainCategoryName": "바디&핸드",
    "imageUrl": "https://www.aesop.com/u1nb1km7t5q7/3FvrdIK7YlsGFOuk0pqlul/901c9195c168abd21e74d2bb854ab2b3/Aesop-Personal-Care-Deodorant-50mL-Large-782x796px.png",
    "ingredients": "[\"정제수\", \"석영\", \"글리세릴스테아레이트에스이\", \"로즈힙씨추출물\", \"글리세린\", \"락틱애씨드\", \"토코페롤\"]"
  },
  {
    "id": 2,
    "name": "사가지 페이셜 엑설런트 페이스트",
    "price": "67000.00",
    "description": "네 가지 성분으로 각질을 관리해주면서 피부를 매끄럽게 해주는 4bsop의 클렌저",
    "sizeId": 5,
    "subCategoryId": 2,
    "size": "75ml",
    "subCategoryName": "각질 제거",
    "mainCategoryId": 2,
    "mainCategoryName": "스킨 케어",
    "imageUrl": "https://www.aesop.com/u1nb1km7t5q7/5WyTfgNAithJEV9QsGzBC0/01068fa32a63c9be0614f5bb65ff98ee/Aesop-Hand-Reverence-Aromatique-Hand-Wash-Refill-500mL-Large-888x1100px.png",
    "ingredients": "[\"정제수\", \"석영\", \"소듐이세티오네이트\", \"코코넛애씨드\", \"라벤더오일\", \"풀루란\", \"로즈마리잎오일\"]"
  },
  {
    "id": 3,
    "name": "위 코 드 퍼퓸",
    "price": "155000.00",
    "description": "남다른 개발자의 느낌을 자아내는 매혹적인 향수. 히노키 숲에서 개발하는 모습을 연상시키며 스모키한 향기로 은은한 개발 욕구를 자극합니다.",
    "sizeId": 6,
    "subCategoryId": 12,
    "size": "50ml",
    "subCategoryName": "우디",
    "mainCategoryId": 1,
    "mainCategoryName": "향수",
    "imageUrl": "https://www.aesop.com/u1nb1km7t5q7/3ZQiTGH2HncEKFSsyMimU3/60cbd0bcd44322ad6ab74bed7a8b01b2/Aesop-Fragrance-Hwyl-Eau-de-Parfum-50mL-Hybris-Large-684x668px.png",
    "ingredients": "[\"글리세릴스테아레이트에스이\", \"글리세린\", \"소듐이세티오네이트\", \"코코넛애씨드\", \"풀루란\"]"
  },
  {
    "id": 4,
    "name": "사가지라이징 샴푸",
    "price": "57000.00",
    "description": "컴퓨터 공학적 추출물이 두피를 자극하지 않고 사가지(four-branch) 있게 유분을 제거해주며 프론트와 백의 밸런스를 도와주는 샴푸",
    "sizeId": 4,
    "subCategoryId": 7,
    "size": "500ml",
    "subCategoryName": "샴푸",
    "mainCategoryId": 4,
    "mainCategoryName": "헤어",
    "imageUrl": "https://www.aesop.com/u1nb1km7t5q7/5VzRlh0YujQHNA8YnyfRCP/3f23da2b1c6593652bd63cffe7f930d4/Aesop-Hair-Equalising-Shampoo-500mL-large.png",
    "ingredients": "[\"정제수\", \"석영\", \"로즈힙씨추출물\", \"글리세린\", \"로즈마리잎오일\"]"
  },
  {
    "id": 5,
    "name": "단백질 샴푸",
    "price": "57000.00",
    "description": "컴퓨터 공학적 추출물이 두피를 자극하지 않고 사가지(four-branch) 있게 유분을 제거해주며 프론트와 백의 밸런스를 도와주는 샴푸",
    "sizeId": 7,
    "subCategoryId": 7,
    "size": "500ml",
    "subCategoryName": "샴푸",
    "mainCategoryId": 4,
    "mainCategoryName": "헤어",
    "imageUrl": "https://www.aesop.com/u1nb1km7t5q7/3ZQiTGH2HncEKFSsyMimU3/60cbd0bcd44322ad6ab74bed7a8b01b2/Aesop-Fragrance-Hwyl-Eau-de-Parfum-50mL-Hybris-Large-684x668px.png",
    "ingredients": "[\"정제수\", \"석영\", \"로즈힙씨추출물\", \"글리세린\", \"로즈마리잎오일\"]"
  },
  {
    "id": 6,
    "name": "그냥 샴푸",
    "price": "57000.00",
    "description": "컴퓨터 공학적 추출물이 두피를 자극하지 않고 사가지(four-branch) 있게 유분을 제거해주며 프론트와 백의 밸런스를 도와주는 샴푸",
    "sizeId": 4,
    "subCategoryId": 7,
    "size": "500ml",
    "subCategoryName": "샴푸",
    "mainCategoryId": 4,
    "mainCategoryName": "헤어",
    "imageUrl": "https://www.aesop.com/u1nb1km7t5q7/5VzRlh0YujQHNA8YnyfRCP/3f23da2b1c6593652bd63cffe7f930d4/Aesop-Hair-Equalising-Shampoo-500mL-large.png",
    "ingredients": "[\"정제수\", \"석영\", \"로즈힙씨추출물\", \"글리세린\", \"로즈마리잎오일\"]"
  },
  {
    "id": 7,
    "name": "써도 괜찮은 샴푸",
    "price": "57000.00",
    "description": "컴퓨터 공학적 추출물이 두피를 자극하지 않고 사가지(four-branch) 있게 유분을 제거해주며 프론트와 백의 밸런스를 도와주는 샴푸",
    "sizeId": 4,
    "subCategoryId": 7,
    "size": "500ml",
    "subCategoryName": "샴푸",
    "mainCategoryId": 4,
    "mainCategoryName": "헤어",
    "imageUrl": "https://www.aesop.com/u1nb1km7t5q7/5VzRlh0YujQHNA8YnyfRCP/3f23da2b1c6593652bd63cffe7f930d4/Aesop-Hair-Equalising-Shampoo-500mL-large.png",
    "ingredients": "[\"정제수\", \"석영\", \"로즈힙씨추출물\", \"글리세린\", \"로즈마리잎오일\"]"
  },
  {
    "id": 8,
    "name": "비싼 샴푸",
    "price": "57000.00",
    "description": "컴퓨터 공학적 추출물이 두피를 자극하지 않고 사가지(four-branch) 있게 유분을 제거해주며 프론트와 백의 밸런스를 도와주는 샴푸",
    "sizeId": 4,
    "subCategoryId": 7,
    "size": "500ml",
    "subCategoryName": "샴푸",
    "mainCategoryId": 4,
    "mainCategoryName": "헤어",
    "imageUrl": "https://www.aesop.com/u1nb1km7t5q7/5VzRlh0YujQHNA8YnyfRCP/3f23da2b1c6593652bd63cffe7f930d4/Aesop-Hair-Equalising-Shampoo-500mL-large.png",
    "ingredients": "[\"정제수\", \"석영\", \"로즈힙씨추출물\", \"글리세린\", \"로즈마리잎오일\"]"
  }
]
